gptools/util/__init__.py
gptools/util/graph.py
gptools/util/kernels.py
gptools/util/plotting.py
gptools/util/testing.py
gptools/util/timeout.py
gptools/util/fft/__init__.py
gptools/util/fft/fft1.py
gptools/util/fft/fft2.py
gptools/util/fft/util.py
tests/conftest.py
tests/test_fft.py
tests/test_graph.py
tests/test_kernels.py
tests/test_plotting.py
tests/test_timeout.py
tests/test_util.py
gptools_util-0.1.2.dist-info/METADATA
gptools_util-0.1.2.dist-info/WHEEL
gptools_util-0.1.2.dist-info/top_level.txt
gptools_util-0.1.2.dist-info/RECORD
