Metadata-Version: 2.2
Name: gptools-util
Version: 0.1.2
Summary: Utility functions for Gaussian processes on graphs and lattices in Stan.
Requires-Python: >=3.8
Requires-Dist: numpy
